ClickReaction/BaseReaction.py
ClickReaction/Exceptions.py
ClickReaction/__init__.py
ClickReaction/Reactions/AlkalineEsterHydrolysis.py
ClickReaction/Reactions/AmideCoupling.py
ClickReaction/Reactions/AmideCouplingWithAnilines.py
ClickReaction/Reactions/BocRemoval.py
ClickReaction/Reactions/CuAAC.py
ClickReaction/Reactions/FmocRemoval.py
ClickReaction/Reactions/SulfonAmideFormation.py
ClickReaction/Reactions/SuzukiMiyaura.py
ClickReaction/Reactions/__init__.py
ClickReaction-0.3.1.dist-info/LICENSE
ClickReaction-0.3.1.dist-info/METADATA
ClickReaction-0.3.1.dist-info/WHEEL
ClickReaction-0.3.1.dist-info/top_level.txt
ClickReaction-0.3.1.dist-info/RECORD
