Metadata-Version: 2.1
Name: ClickReaction
Version: 0.3.1
Summary: A collection of chemical reaction formulations for use with rdkit. Requires rdkit.
Home-page: https://github.com/Gillingham-Lab/Click
Author: Basilius Sauter
Author-email: basilius.sauter@gmail.com
License: UNKNOWN
Platform: UNKNOWN
Classifier: Programming Language :: Python :: 3
Classifier: License :: OSI Approved :: MIT License
Classifier: Operating System :: OS Independent
Classifier: Intended Audience :: Science/Research
Classifier: Topic :: Scientific/Engineering :: Chemistry
Classifier: Topic :: Scientific/Engineering :: Bio-Informatics
Classifier: Topic :: Software Development :: Libraries :: Python Modules
Classifier: Topic :: Utilities
Requires-Python: >=3.6
